datadog_custom_logger/__init__.py
datadog_custom_logger/handler.py
datadog_custom_logger-0.1.0.dist-info/LICENSE
datadog_custom_logger-0.1.0.dist-info/METADATA
datadog_custom_logger-0.1.0.dist-info/WHEEL
datadog_custom_logger-0.1.0.dist-info/top_level.txt
datadog_custom_logger-0.1.0.dist-info/zip-safe
datadog_custom_logger-0.1.0.dist-info/RECORD
